odoo/addons/sale_channel_product/README.rst
odoo/addons/sale_channel_product/__init__.py
odoo/addons/sale_channel_product/__manifest__.py
odoo/addons/sale_channel_product/i18n/it.po
odoo/addons/sale_channel_product/i18n/sale_channel_product.pot
odoo/addons/sale_channel_product/models/__init__.py
odoo/addons/sale_channel_product/models/product_template.py
odoo/addons/sale_channel_product/static/description/icon.png
odoo/addons/sale_channel_product/views/product_template_view.xml
odoo_addon_sale_channel_product-18.0.1.0.0.1.dist-info/METADATA
odoo_addon_sale_channel_product-18.0.1.0.0.1.dist-info/WHEEL
odoo_addon_sale_channel_product-18.0.1.0.0.1.dist-info/top_level.txt
odoo_addon_sale_channel_product-18.0.1.0.0.1.dist-info/RECORD
